proBait/__init__.py
proBait/cluster_utils.py
proBait/constants.py
proBait/general_utils.py
proBait/map_utils.py
proBait/proBait.py
proBait/report_utils.py
proBait-0.1.0.dist-info/LICENSE
proBait-0.1.0.dist-info/METADATA
proBait-0.1.0.dist-info/WHEEL
proBait-0.1.0.dist-info/entry_points.txt
proBait-0.1.0.dist-info/top_level.txt
proBait-0.1.0.dist-info/RECORD
