Metadata-Version: 2.1
Name: proBait
Version: 0.1.0
Summary: Generate target-enrichment probes from a set of genome assemblies.
Author: Rafael Mamede, Mário Ramirez
Maintainer-email: UMMI <imm-bioinfo@medicina.ulisboa.pt>
License: GNU GENERAL PUBLIC LICENSE
Project-URL: Repository, https://github.com/B-UMMI/proBait
Project-URL: Changelog, https://github.com/B-UMMI/proBait/blob/master/CHANGELOG.md
Keywords: bioinformatics,genomics,target capture,target-enrichment
Classifier: Development Status :: 5 - Production/Stable
Classifier: Environment :: Console
Classifier: Intended Audience :: Science/Research
Classifier: License :: OSI Approved :: GNU General Public License v3 (GPLv3)
Classifier: Natural Language :: English
Classifier: Operating System :: Unix
Classifier: Programming Language :: Python :: 3.11
Classifier: Programming Language :: Python :: Implementation :: CPython
Classifier: Topic :: Scientific/Engineering :: Bio-Informatics
Requires-Python: >=3.11
License-File: LICENSE
Requires-Dist: biopython >=1.83
Requires-Dist: plotly >=5.22.0
Requires-Dist: pandas >=1.5.3
Requires-Dist: datapane >=0.17.0
